pyaioconsole/__init__.py
pyaioconsole/app/__init__.py
pyaioconsole/app/config.py
pyaioconsole/commands.py
pyaioconsole/depends.py
pyaioconsole-0.1.1.dist-info/LICENSE
pyaioconsole-0.1.1.dist-info/METADATA
pyaioconsole-0.1.1.dist-info/WHEEL
pyaioconsole-0.1.1.dist-info/RECORD
