Metadata-Version: 2.1
Name: pyaioconsole
Version: 0.1.1
Summary: Python library for creating async CLI applications
License: MIT
Author: alexeev-prog
Author-email: alexeev.dev@mail.ru
Requires-Python: >=3.10,<4.0
Classifier: License :: OSI Approved :: MIT License
Classifier: Programming Language :: Python :: 3
Classifier: Programming Language :: Python :: 3.10
Classifier: Programming Language :: Python :: 3.11
Classifier: Programming Language :: Python :: 3.12
Requires-Dist: asyncio (>=3.4.3,<4.0.0)
Requires-Dist: python-dotenv (>=1.0.1,<2.0.0)
Requires-Dist: rich (>=13.9.4,<14.0.0)
